whatsonthemenu/__init__.py
whatsonthemenu-0.0.1.dist-info/DESCRIPTION.rst
whatsonthemenu-0.0.1.dist-info/METADATA
whatsonthemenu-0.0.1.dist-info/RECORD
whatsonthemenu-0.0.1.dist-info/WHEEL
whatsonthemenu-0.0.1.dist-info/metadata.json
whatsonthemenu-0.0.1.dist-info/top_level.txt
