Metadata-Version: 2.0
Name: whatsonthemenu
Version: 0.0.1
Summary: Python interface to NYPL's What's on The Menu API
Home-page: https://github.com/hugovk/whatsonthemenu
Author: hugovk
Author-email: UNKNOWN
License: UNKNOWN
Platform: UNKNOWN
